rsquant/__init__.py
rsquant/__main__.py
rsquant/_version.py
rsquant/benchmarks.py
rsquant/common_holidays.py
rsquant/exchange_calendar_xsge.py
rsquant/exchange_calendar_xshg.py
rsquant/holidays_cn.txt
rsquant/quantrs.py
rsquant/utils/__init__.py
rsquant/utils/compat.py
rsquant/utils/memoize.py
rsquant/utils/pandas_utils.py
rsquant/utils/preprocess.py
rsquant-0.1.2.dist-info/LICENSE.txt
rsquant-0.1.2.dist-info/METADATA
rsquant-0.1.2.dist-info/RECORD
rsquant-0.1.2.dist-info/WHEEL
rsquant-0.1.2.dist-info/entry_points.txt
rsquant-0.1.2.dist-info/top_level.txt
